lyra/__init__.py
lyra/cli.py
lyra/constants.py
lyra/enums.py
lyra/lyra.py
lyra/utils.py
lyra_client-0.1.2.dist-info/METADATA
lyra_client-0.1.2.dist-info/WHEEL
lyra_client-0.1.2.dist-info/entry_points.txt
lyra_client-0.1.2.dist-info/RECORD
