Metadata-Version: 2.1
Name: lyra-client
Version: 0.1.2
Summary: 
Author: 8baller
Author-email: 8ball030@gmail.com
Requires-Python: >=3.8.1,<=3.11.5
Classifier: Programming Language :: Python :: 3
Classifier: Programming Language :: Python :: 3.9
Classifier: Programming Language :: Python :: 3.10
Classifier: Programming Language :: Python :: 3.11
Requires-Dist: python-dotenv (>=0.14.0,<0.18.0)
Requires-Dist: requests (>=2.31.0,<3.0.0)
Requires-Dist: rich-click (>=1.7.1,<2.0.0)
Requires-Dist: setuptools (>=68.2.2,<69.0.0)
Requires-Dist: web3 (>=5,<6)
Requires-Dist: websocket-client (>=1.6.4,<2.0.0)
